climate_metrics.py
climate_metrics-2022.1.0.dist-info/License.txt
climate_metrics-2022.1.0.dist-info/METADATA
climate_metrics-2022.1.0.dist-info/WHEEL
climate_metrics-2022.1.0.dist-info/top_level.txt
climate_metrics-2022.1.0.dist-info/RECORD
