Metadata-Version: 2.1
Name: climate-metrics
Version: 2022.1.0
Summary: Climate metrics for greenhouse gas accounting
Home-page: https://github.com/BlaneG/climate_metrics
Author: Blane Grann
License: MIT License
Keywords: GWP,GTP,global warming potential,global temperature change potential,GHG,greenhouse gas,climate metrics
Platform: UNKNOWN
Classifier: Programming Language :: Python :: 3.7
Classifier: Programming Language :: Python :: 3.8
Classifier: Programming Language :: Python :: 3.9
Requires-Python: >=3.7
License-File: License.txt
Requires-Dist: numpy
Requires-Dist: scipy
